statspost/__init__.py
statspost/_type.py
statspost/client.py
statspost/enums.py
statspost/errors.py
statspost/http.py
statspost/py.typed
statspost.py-1.0.1.dist-info/LICENSE
statspost.py-1.0.1.dist-info/METADATA
statspost.py-1.0.1.dist-info/WHEEL
statspost.py-1.0.1.dist-info/top_level.txt
statspost.py-1.0.1.dist-info/RECORD
