Metadata-Version: 2.1
Name: statspost.py
Version: 1.0.1
Summary: A Python wrapper for the Fluxpoint API
Home-page: https://github.com/Dhruvacube/statspost.py
Author: Dhruva Shaw
License: MIT
Project-URL: Documentation, https://statspost.dhruvashaw.me
Project-URL: Issue tracker, https://github.com/Dhruvacube/statspost.py/issues
Classifier: Development Status :: 2 - Pre-Alpha
Classifier: License :: OSI Approved :: MIT License
Classifier: Intended Audience :: Developers
Classifier: Natural Language :: English
Classifier: Operating System :: OS Independent
Classifier: Programming Language :: Python :: 3
Classifier: Programming Language :: Python :: 3.8
Classifier: Programming Language :: Python :: 3.9
Classifier: Topic :: Internet
Classifier: Topic :: Software Development :: Libraries
Classifier: Topic :: Software Development :: Libraries :: Python Modules
Classifier: Topic :: Utilities
Classifier: Typing :: Typed
Requires-Python: >=3.8
License-File: LICENSE
Requires-Dist: aiohttp (>=3.8.1)
Provides-Extra: discord
Requires-Dist: discord.py (>=2.0.0) ; extra == 'discord'
Provides-Extra: docs
Requires-Dist: sphinx ; extra == 'docs'
Requires-Dist: sphinxcontrib-trio ; extra == 'docs'
Requires-Dist: sphinxcontrib-websupport ; extra == 'docs'
Requires-Dist: sphinx-autoapi ; extra == 'docs'
Requires-Dist: typing-extensions ; extra == 'docs'
Provides-Extra: speed
Requires-Dist: aiohttp[speedups] (>=3.8.1) ; extra == 'speed'
